shublang/__init__.py
shublang/cmdline.py
shublang/constants.py
shublang/parser.py
shublang/shublang.py
tests/__init__.py
tests/test_functions.py
tests/test_statement_parser.py
shublang-0.2.2.dist-info/LICENSE
shublang-0.2.2.dist-info/METADATA
shublang-0.2.2.dist-info/WHEEL
shublang-0.2.2.dist-info/entry_points.txt
shublang-0.2.2.dist-info/top_level.txt
shublang-0.2.2.dist-info/RECORD
